{
  "Ein Frankfurt": [
    927,
    1167,
    1262,
    1342,
    1303,
    1186,
    983,
    696,
    463,
    292,
    167,
    122,
    51,
    27,
    8,
    3,
    0,
    1
  ],
  "Bayern Munich": [
    3547,
    2122,
    1435,
    980,
    744,
    514,
    300,
    187,
    91,
    45,
    26,
    5,
    2,
    2,
    0,
    0,
    0,
    0
  ],
  "Augsburg": [
    4,
    17,
    25,
    45,
    94,
    169,
    263,
    390,
    595,
    776,
    892,
    955,
    1110,
    1160,
    1201,
    1051,
    855,
    398
  ],
  "Freiburg": [
    887,
    1158,
    1279,
    1304,
    1270,
    1166,
    990,
    739,
    477,
    325,
    178,
    120,
    56,
    26,
    19,
    6,
    0,
    0
  ],
  "Bochum": [
    0,
    1,
    11,
    15,
    42,
    85,
    149,
    267,
    357,
    510,
    675,
    817,
    1010,
    1138,
    1354,
    1464,
    1342,
    763
  ],
  "Mainz": [
    6,
    24,
    60,
    104,
    192,
    267,
    464,
    599,
    849,
    923,
    1003,
    1164,
    1065,
    1006,
    890,
    709,
    482,
    193
  ],
  "M'gladbach": [
    26,
    74,
    124,
    219,
    320,
    540,
    711,
    914,
    1093,
    1160,
    1115,
    982,
    856,
    703,
    555,
    356,
    200,
    52
  ],
  "Hoffenheim": [
    1,
    15,
    30,
    67,
    116,
    204,
    336,
    543,
    715,
    832,
    1004,
    1056,
    1088,
    1149,
    1098,
    879,
    611,
    256
  ],
  "Union Berlin": [
    1747,
    1721,
    1509,
    1375,
    1125,
    875,
    688,
    416,
    245,
    141,
    84,
    45,
    14,
    11,
    3,
    1,
    0,
    0
  ],
  "Hertha": [
    0,
    0,
    5,
    7,
    8,
    24,
    45,
    126,
    189,
    290,
    401,
    521,
    739,
    962,
    1152,
    1632,
    2223,
    1676
  ],
  "Wolfsburg": [
    474,
    720,
    980,
    1104,
    1228,
    1221,
    1165,
    946,
    760,
    527,
    381,
    237,
    113,
    76,
    33,
    25,
    9,
    1
  ],
  "Werder Bremen": [
    7,
    54,
    103,
    141,
    240,
    393,
    581,
    775,
    903,
    1008,
    1051,
    1081,
    1032,
    896,
    721,
    565,
    340,
    109
  ],
  "Dortmund": [
    1095,
    1289,
    1285,
    1346,
    1213,
    1157,
    923,
    638,
    434,
    245,
    183,
    102,
    47,
    26,
    14,
    1,
    2,
    0
  ],
  "Leverkusen": [
    68,
    176,
    298,
    378,
    570,
    813,
    966,
    1163,
    1208,
    1061,
    972,
    759,
    598,
    424,
    289,
    158,
    79,
    20
  ],
  "Stuttgart": [
    0,
    1,
    11,
    20,
    39,
    67,
    114,
    207,
    295,
    460,
    568,
    788,
    915,
    1116,
    1312,
    1581,
    1560,
    946
  ],
  "RB Leipzig": [
    1195,
    1431,
    1480,
    1401,
    1230,
    1013,
    795,
    608,
    367,
    225,
    124,
    69,
    29,
    22,
    4,
    5,
    2,
    0
  ],
  "FC Koln": [
    16,
    30,
    103,
    152,
    264,
    305,
    523,
    776,
    930,
    1127,
    1087,
    1041,
    1034,
    879,
    737,
    549,
    322,
    125
  ],
  "Schalke 04": [
    0,
    0,
    0,
    0,
    2,
    1,
    4,
    10,
    29,
    53,
    89,
    136,
    241,
    377,
    610,
    1015,
    1973,
    5460
  ]
}