{
  "Monaco": [
    1,
    56,
    202,
    393,
    540,
    648,
    763,
    891,
    892,
    983,
    931,
    947,
    877,
    744,
    625,
    326,
    129,
    43,
    8,
    1
  ],
  "Nantes": [
    0,
    15,
    103,
    181,
    272,
    405,
    504,
    633,
    720,
    915,
    1002,
    992,
    1104,
    1090,
    1009,
    631,
    300,
    91,
    29,
    4
  ],
  "Lyon": [
    6,
    282,
    794,
    1009,
    1175,
    1088,
    1067,
    958,
    823,
    754,
    576,
    507,
    372,
    282,
    200,
    75,
    29,
    3,
    0,
    0
  ],
  "Brest": [
    0,
    0,
    0,
    0,
    0,
    1,
    0,
    2,
    6,
    6,
    11,
    19,
    39,
    73,
    217,
    572,
    1223,
    2334,
    2887,
    2610
  ],
  "Troyes": [
    0,
    0,
    0,
    3,
    13,
    21,
    39,
    63,
    115,
    166,
    218,
    361,
    587,
    810,
    1375,
    2131,
    2093,
    1274,
    532,
    199
  ],
  "Paris SG": [
    8984,
    877,
    108,
    24,
    4,
    2,
    0,
    0,
    1,
    0,
    0,
    0,
    0,
    0,
    0,
    0,
    0,
    0,
    0,
    0
  ],
  "Rennes": [
    8,
    192,
    618,
    902,
    1005,
    1068,
    1050,
    964,
    881,
    766,
    703,
    590,
    480,
    374,
    232,
    117,
    42,
    7,
    1,
    0
  ],
  "Lens": [
    110,
    1385,
    2544,
    1805,
    1235,
    920,
    673,
    449,
    311,
    221,
    149,
    106,
    51,
    21,
    14,
    4,
    2,
    0,
    0,
    0
  ],
  "Bordeaux": [
    0,
    0,
    1,
    6,
    7,
    19,
    29,
    44,
    75,
    96,
    166,
    270,
    392,
    601,
    1051,
    1998,
    2523,
    1558,
    846,
    318
  ],
  "Clermont": [
    0,
    19,
    87,
    149,
    317,
    379,
    450,
    580,
    763,
    817,
    946,
    960,
    1137,
    1149,
    1066,
    697,
    374,
    85,
    24,
    1
  ],
  "Nice": [
    58,
    952,
    1826,
    1701,
    1316,
    1043,
    839,
    649,
    500,
    387,
    260,
    168,
    149,
    87,
    42,
    17,
    5,
    0,
    0,
    1
  ],
  "Reims": [
    0,
    9,
    61,
    112,
    162,
    276,
    360,
    455,
    557,
    689,
    793,
    1007,
    1183,
    1241,
    1304,
    976,
    551,
    201,
    50,
    13
  ],
  "St Etienne": [
    0,
    0,
    0,
    0,
    0,
    0,
    0,
    1,
    0,
    1,
    6,
    6,
    16,
    45,
    98,
    290,
    789,
    1832,
    2725,
    4191
  ],
  "Lorient": [
    6,
    225,
    608,
    968,
    1107,
    1116,
    1008,
    968,
    901,
    770,
    651,
    560,
    438,
    330,
    204,
    98,
    32,
    8,
    2,
    0
  ],
  "Strasbourg": [
    0,
    21,
    91,
    207,
    306,
    476,
    536,
    677,
    773,
    879,
    957,
    1024,
    1055,
    1088,
    883,
    610,
    319,
    75,
    20,
    3
  ],
  "Angers": [
    8,
    245,
    731,
    1002,
    1167,
    1077,
    1092,
    977,
    839,
    736,
    636,
    535,
    379,
    301,
    165,
    78,
    28,
    4,
    0,
    0
  ],
  "Metz": [
    0,
    0,
    0,
    0,
    0,
    1,
    1,
    1,
    1,
    2,
    9,
    20,
    41,
    73,
    203,
    561,
    1179,
    2390,
    2859,
    2659
  ],
  "Lille": [
    0,
    77,
    240,
    414,
    575,
    712,
    850,
    877,
    955,
    862,
    974,
    938,
    761,
    750,
    526,
    317,
    132,
    37,
    3,
    0
  ],
  "Montpellier": [
    0,
    34,
    138,
    296,
    418,
    550,
    616,
    726,
    845,
    915,
    1000,
    983,
    931,
    940,
    784,
    502,
    250,
    58,
    14,
    0
  ],
  "Marseille": [
    819,
    5611,
    1848,
    828,
    381,
    198,
    123,
    85,
    42,
    35,
    12,
    7,
    8,
    1,
    2,
    0,
    0,
    0,
    0,
    0
  ]
}