{
  "Fortaleza / CE": [
    12,
    38,
    88,
    167,
    245,
    383,
    490,
    637,
    769,
    925,
    910,
    849,
    895,
    803,
    776,
    741,
    580,
    381,
    235,
    76
  ],
  "Athletico Paranaense / PR": [
    7,
    24,
    51,
    100,
    166,
    279,
    378,
    483,
    660,
    753,
    909,
    915,
    962,
    911,
    880,
    824,
    678,
    550,
    353,
    117
  ],
  "Coritiba / PR": [
    0,
    0,
    0,
    6,
    3,
    9,
    15,
    33,
    66,
    89,
    144,
    217,
    295,
    406,
    583,
    814,
    1071,
    1619,
    2216,
    2414
  ],
  "Internacional / RS": [
    697,
    934,
    1100,
    1145,
    1197,
    1087,
    1041,
    780,
    607,
    432,
    338,
    216,
    167,
    121,
    77,
    32,
    23,
    5,
    1,
    0
  ],
  "Sport / PE": [
    7,
    19,
    48,
    55,
    109,
    176,
    255,
    343,
    475,
    610,
    701,
    778,
    866,
    937,
    988,
    979,
    922,
    858,
    584,
    290
  ],
  "Ceará / CE": [
    6,
    20,
    42,
    82,
    107,
    190,
    256,
    383,
    459,
    629,
    705,
    880,
    848,
    951,
    980,
    1002,
    859,
    779,
    585,
    237
  ],
  "Flamengo / RJ": [
    1593,
    1638,
    1565,
    1253,
    1072,
    891,
    660,
    473,
    329,
    205,
    124,
    82,
    55,
    26,
    22,
    10,
    1,
    0,
    1,
    0
  ],
  "Atlético Mineiro / MG": [
    2583,
    2095,
    1591,
    1184,
    853,
    612,
    422,
    283,
    144,
    117,
    47,
    30,
    22,
    12,
    5,
    0,
    0,
    0,
    0,
    0
  ],
  "Santos / SP": [
    309,
    512,
    703,
    875,
    1007,
    1048,
    1034,
    1012,
    847,
    732,
    555,
    451,
    312,
    252,
    157,
    108,
    46,
    27,
    11,
    2
  ],
  "Red Bull Bragantino / SP": [
    5,
    15,
    45,
    75,
    129,
    213,
    333,
    431,
    562,
    640,
    786,
    843,
    931,
    939,
    901,
    917,
    881,
    661,
    478,
    215
  ],
  "Grêmio / RS": [
    552,
    776,
    947,
    1017,
    1091,
    1068,
    967,
    891,
    712,
    577,
    419,
    341,
    241,
    164,
    104,
    78,
    40,
    10,
    5,
    0
  ],
  "Fluminense / RJ": [
    475,
    712,
    905,
    1067,
    1164,
    1136,
    982,
    912,
    769,
    552,
    381,
    301,
    226,
    163,
    122,
    76,
    42,
    11,
    4,
    0
  ],
  "Botafogo / RJ": [
    0,
    1,
    1,
    4,
    9,
    10,
    21,
    48,
    74,
    112,
    171,
    244,
    331,
    439,
    572,
    850,
    1195,
    1641,
    2046,
    2231
  ],
  "Corinthians / SP": [
    10,
    47,
    66,
    177,
    218,
    353,
    514,
    582,
    762,
    817,
    934,
    894,
    964,
    877,
    775,
    699,
    625,
    387,
    213,
    86
  ],
  "Goiás / GO": [
    0,
    0,
    0,
    1,
    2,
    8,
    7,
    18,
    38,
    51,
    77,
    127,
    192,
    244,
    413,
    555,
    841,
    1366,
    2226,
    3834
  ],
  "Bahia / BA": [
    31,
    63,
    129,
    208,
    273,
    387,
    533,
    700,
    739,
    849,
    884,
    930,
    847,
    827,
    812,
    622,
    540,
    360,
    192,
    74
  ],
  "Atlético Goianiense / GO": [
    12,
    29,
    77,
    139,
    204,
    299,
    402,
    526,
    683,
    748,
    870,
    924,
    881,
    876,
    828,
    745,
    732,
    549,
    329,
    147
  ],
  "Palmeiras / SP": [
    888,
    1171,
    1195,
    1247,
    1157,
    1033,
    910,
    725,
    533,
    391,
    257,
    202,
    125,
    80,
    41,
    23,
    17,
    5,
    0,
    0
  ],
  "São Paulo / SP": [
    2807,
    1885,
    1394,
    1116,
    853,
    619,
    471,
    321,
    198,
    142,
    84,
    51,
    29,
    19,
    8,
    1,
    2,
    0,
    0,
    0
  ],
  "Vasco da Gama / RJ": [
    6,
    21,
    53,
    82,
    141,
    199,
    309,
    419,
    574,
    629,
    704,
    725,
    811,
    953,
    956,
    924,
    905,
    791,
    521,
    277
  ]
}