{
  "Brentford": [
    0,
    0,
    0,
    0,
    0,
    0,
    2,
    36,
    723,
    1601,
    1741,
    1723,
    1565,
    1263,
    1077,
    246,
    23,
    0,
    0,
    0
  ],
  "Arsenal": [
    0,
    0,
    288,
    4302,
    4354,
    840,
    180,
    36,
    0,
    0,
    0,
    0,
    0,
    0,
    0,
    0,
    0,
    0,
    0,
    0
  ],
  "Man United": [
    0,
    0,
    4,
    227,
    1089,
    4556,
    2864,
    1189,
    71,
    0,
    0,
    0,
    0,
    0,
    0,
    0,
    0,
    0,
    0,
    0
  ],
  "Leeds": [
    0,
    0,
    0,
    0,
    0,
    0,
    0,
    0,
    3,
    22,
    57,
    85,
    200,
    390,
    854,
    4675,
    3025,
    680,
    9,
    0
  ],
  "Burnley": [
    0,
    0,
    0,
    0,
    0,
    0,
    0,
    0,
    0,
    0,
    0,
    2,
    18,
    37,
    91,
    670,
    2069,
    5570,
    1226,
    317
  ],
  "Brighton": [
    0,
    0,
    0,
    0,
    0,
    0,
    1,
    85,
    743,
    1672,
    1811,
    1700,
    1541,
    1274,
    942,
    211,
    20,
    0,
    0,
    0
  ],
  "Chelsea": [
    0,
    7,
    9418,
    525,
    47,
    3,
    0,
    0,
    0,
    0,
    0,
    0,
    0,
    0,
    0,
    0,
    0,
    0,
    0,
    0
  ],
  "Crystal Palace": [
    0,
    0,
    0,
    0,
    0,
    0,
    2,
    29,
    686,
    1644,
    1596,
    1449,
    1367,
    1370,
    1305,
    450,
    99,
    3,
    0,
    0
  ],
  "Everton": [
    0,
    0,
    0,
    0,
    0,
    0,
    0,
    0,
    0,
    7,
    15,
    43,
    74,
    140,
    405,
    2517,
    4358,
    2206,
    219,
    16
  ],
  "Southampton": [
    0,
    0,
    0,
    0,
    0,
    0,
    1,
    34,
    645,
    1233,
    1342,
    1448,
    1545,
    1669,
    1631,
    408,
    42,
    2,
    0,
    0
  ],
  "Leicester": [
    0,
    0,
    0,
    0,
    1,
    41,
    163,
    854,
    5120,
    1766,
    946,
    540,
    322,
    163,
    75,
    9,
    0,
    0,
    0,
    0
  ],
  "Wolves": [
    0,
    0,
    0,
    7,
    125,
    1265,
    2695,
    4936,
    872,
    89,
    11,
    0,
    0,
    0,
    0,
    0,
    0,
    0,
    0,
    0
  ],
  "Watford": [
    0,
    0,
    0,
    0,
    0,
    0,
    0,
    0,
    0,
    0,
    0,
    0,
    0,
    0,
    0,
    25,
    189,
    1012,
    5269,
    3505
  ],
  "Aston Villa": [
    0,
    0,
    0,
    0,
    0,
    0,
    8,
    45,
    622,
    1069,
    1215,
    1425,
    1477,
    1633,
    1883,
    500,
    105,
    18,
    0,
    0
  ],
  "Norwich": [
    0,
    0,
    0,
    0,
    0,
    0,
    0,
    0,
    0,
    0,
    0,
    0,
    0,
    0,
    0,
    3,
    49,
    509,
    3277,
    6162
  ],
  "Liverpool": [
    3872,
    6123,
    5,
    0,
    0,
    0,
    0,
    0,
    0,
    0,
    0,
    0,
    0,
    0,
    0,
    0,
    0,
    0,
    0,
    0
  ],
  "Newcastle": [
    0,
    0,
    0,
    0,
    0,
    0,
    0,
    4,
    259,
    890,
    1266,
    1585,
    1891,
    2061,
    1737,
    286,
    21,
    0,
    0,
    0
  ],
  "West Ham": [
    0,
    0,
    1,
    42,
    357,
    2638,
    3964,
    2735,
    256,
    7,
    0,
    0,
    0,
    0,
    0,
    0,
    0,
    0,
    0,
    0
  ],
  "Tottenham": [
    0,
    0,
    282,
    4897,
    4027,
    657,
    120,
    17,
    0,
    0,
    0,
    0,
    0,
    0,
    0,
    0,
    0,
    0,
    0,
    0
  ],
  "Man City": [
    6128,
    3870,
    2,
    0,
    0,
    0,
    0,
    0,
    0,
    0,
    0,
    0,
    0,
    0,
    0,
    0,
    0,
    0,
    0,
    0
  ]
}