{
  "Liverpool": [
    10000,
    0,
    0,
    0,
    0,
    0,
    0,
    0,
    0,
    0,
    0,
    0,
    0,
    0,
    0,
    0,
    0,
    0,
    0,
    0
  ],
  "Norwich": [
    0,
    0,
    0,
    0,
    0,
    0,
    0,
    1,
    4,
    25,
    45,
    136,
    245,
    496,
    754,
    979,
    1203,
    1501,
    1762,
    2849
  ],
  "West Ham": [
    0,
    0,
    0,
    0,
    0,
    2,
    5,
    21,
    39,
    108,
    276,
    517,
    875,
    1411,
    1423,
    1332,
    1243,
    1153,
    901,
    694
  ],
  "Man City": [
    0,
    9336,
    603,
    54,
    6,
    1,
    0,
    0,
    0,
    0,
    0,
    0,
    0,
    0,
    0,
    0,
    0,
    0,
    0,
    0
  ],
  "Bournemouth": [
    0,
    0,
    0,
    0,
    0,
    0,
    1,
    4,
    17,
    55,
    101,
    287,
    492,
    735,
    1035,
    1289,
    1419,
    1567,
    1596,
    1402
  ],
  "Sheffield United": [
    0,
    13,
    528,
    1556,
    1484,
    1441,
    1299,
    1096,
    1044,
    698,
    455,
    230,
    110,
    31,
    11,
    3,
    1,
    0,
    0,
    0
  ],
  "Burnley": [
    0,
    0,
    32,
    207,
    391,
    621,
    773,
    1089,
    1326,
    1680,
    1487,
    1120,
    675,
    332,
    150,
    75,
    28,
    13,
    0,
    1
  ],
  "Southampton": [
    0,
    0,
    5,
    35,
    90,
    167,
    282,
    487,
    679,
    1137,
    1583,
    1644,
    1451,
    1013,
    647,
    363,
    208,
    127,
    60,
    22
  ],
  "Crystal Palace": [
    0,
    0,
    6,
    32,
    80,
    157,
    244,
    396,
    626,
    976,
    1458,
    1703,
    1711,
    1148,
    645,
    417,
    236,
    115,
    41,
    9
  ],
  "Everton": [
    0,
    0,
    2,
    44,
    96,
    184,
    311,
    511,
    755,
    1143,
    1545,
    1722,
    1498,
    1033,
    583,
    303,
    170,
    72,
    26,
    2
  ],
  "Watford": [
    0,
    0,
    0,
    0,
    0,
    0,
    1,
    14,
    23,
    53,
    137,
    277,
    461,
    785,
    1049,
    1218,
    1377,
    1521,
    1562,
    1522
  ],
  "Brighton": [
    0,
    0,
    0,
    0,
    0,
    1,
    2,
    8,
    23,
    66,
    125,
    270,
    494,
    794,
    1130,
    1298,
    1470,
    1434,
    1550,
    1335
  ],
  "Tottenham": [
    0,
    1,
    248,
    826,
    1064,
    1240,
    1353,
    1331,
    1315,
    1142,
    699,
    417,
    224,
    91,
    32,
    14,
    1,
    2,
    0,
    0
  ],
  "Aston Villa": [
    0,
    0,
    0,
    0,
    0,
    4,
    4,
    12,
    29,
    78,
    167,
    312,
    542,
    806,
    1041,
    1190,
    1279,
    1350,
    1559,
    1627
  ],
  "Leicester": [
    0,
    602,
    6704,
    1533,
    664,
    305,
    127,
    44,
    12,
    8,
    1,
    0,
    0,
    0,
    0,
    0,
    0,
    0,
    0,
    0
  ],
  "Wolves": [
    0,
    14,
    534,
    1698,
    1653,
    1461,
    1333,
    1147,
    929,
    571,
    366,
    181,
    88,
    19,
    5,
    0,
    1,
    0,
    0,
    0
  ],
  "Newcastle": [
    0,
    0,
    0,
    0,
    0,
    4,
    5,
    21,
    55,
    105,
    244,
    516,
    842,
    1233,
    1473,
    1514,
    1363,
    1145,
    943,
    537
  ],
  "Arsenal": [
    0,
    12,
    388,
    1124,
    1357,
    1421,
    1389,
    1349,
    1110,
    823,
    534,
    288,
    144,
    43,
    15,
    2,
    1,
    0,
    0,
    0
  ],
  "Man United": [
    0,
    14,
    616,
    1637,
    1678,
    1491,
    1347,
    1131,
    859,
    584,
    353,
    178,
    81,
    22,
    6,
    3,
    0,
    0,
    0,
    0
  ],
  "Chelsea": [
    0,
    8,
    334,
    1254,
    1437,
    1500,
    1524,
    1338,
    1155,
    748,
    424,
    202,
    67,
    8,
    1,
    0,
    0,
    0,
    0,
    0
  ]
}