{
  "Burnley": [
    0,
    0,
    0,
    0,
    0,
    0,
    0,
    0,
    0,
    0,
    0,
    0,
    0,
    0,
    5,
    21,
    279,
    1470,
    3548,
    4677
  ],
  "Man City": [
    453,
    940,
    1834,
    3173,
    2356,
    842,
    260,
    102,
    28,
    7,
    4,
    0,
    1,
    0,
    0,
    0,
    0,
    0,
    0,
    0
  ],
  "Arsenal": [
    2941,
    2808,
    2359,
    1290,
    470,
    107,
    23,
    1,
    1,
    0,
    0,
    0,
    0,
    0,
    0,
    0,
    0,
    0,
    0,
    0
  ],
  "Nott'm Forest": [
    0,
    0,
    0,
    0,
    0,
    1,
    0,
    1,
    2,
    13,
    32,
    65,
    168,
    394,
    816,
    1825,
    4516,
    1686,
    409,
    72
  ],
  "Bournemouth": [
    0,
    0,
    1,
    2,
    7,
    76,
    219,
    429,
    698,
    958,
    1346,
    1574,
    1659,
    1421,
    915,
    522,
    157,
    15,
    1,
    0
  ],
  "West Ham": [
    0,
    5,
    12,
    104,
    371,
    1150,
    1854,
    1817,
    1556,
    1260,
    817,
    557,
    299,
    131,
    58,
    6,
    3,
    0,
    0,
    0
  ],
  "Brighton": [
    1,
    1,
    6,
    38,
    242,
    799,
    1430,
    1759,
    1748,
    1501,
    1040,
    743,
    404,
    180,
    88,
    17,
    3,
    0,
    0,
    0
  ],
  "Luton": [
    0,
    0,
    0,
    0,
    0,
    0,
    0,
    0,
    0,
    1,
    2,
    3,
    13,
    40,
    111,
    365,
    1517,
    4475,
    2354,
    1119
  ],
  "Everton": [
    0,
    0,
    7,
    22,
    141,
    523,
    1067,
    1420,
    1677,
    1577,
    1351,
    1004,
    622,
    375,
    149,
    58,
    7,
    0,
    0,
    0
  ],
  "Fulham": [
    0,
    0,
    1,
    1,
    8,
    82,
    206,
    446,
    748,
    1081,
    1488,
    1647,
    1553,
    1332,
    888,
    419,
    93,
    7,
    0,
    0
  ],
  "Sheffield United": [
    0,
    0,
    0,
    0,
    0,
    0,
    0,
    0,
    0,
    0,
    0,
    0,
    0,
    3,
    9,
    71,
    363,
    1803,
    3625,
    4126
  ],
  "Crystal Palace": [
    0,
    0,
    0,
    0,
    0,
    0,
    5,
    21,
    40,
    110,
    262,
    401,
    899,
    1412,
    2179,
    2856,
    1487,
    286,
    37,
    5
  ],
  "Newcastle": [
    11,
    60,
    222,
    694,
    1747,
    3172,
    1890,
    1061,
    587,
    322,
    126,
    71,
    23,
    11,
    3,
    0,
    0,
    0,
    0,
    0
  ],
  "Aston Villa": [
    3113,
    2946,
    2241,
    1158,
    420,
    95,
    21,
    4,
    1,
    1,
    0,
    0,
    0,
    0,
    0,
    0,
    0,
    0,
    0,
    0
  ],
  "Brentford": [
    0,
    0,
    0,
    0,
    1,
    7,
    23,
    73,
    130,
    313,
    559,
    864,
    1380,
    1857,
    2168,
    1730,
    757,
    124,
    13,
    1
  ],
  "Tottenham": [
    122,
    421,
    1045,
    2329,
    3372,
    1671,
    630,
    254,
    106,
    39,
    11,
    0,
    0,
    0,
    0,
    0,
    0,
    0,
    0,
    0
  ],
  "Chelsea": [
    0,
    0,
    0,
    6,
    32,
    140,
    383,
    647,
    1019,
    1362,
    1654,
    1593,
    1399,
    911,
    533,
    255,
    60,
    6,
    0,
    0
  ],
  "Liverpool": [
    3359,
    2814,
    2244,
    1064,
    411,
    93,
    12,
    2,
    1,
    0,
    0,
    0,
    0,
    0,
    0,
    0,
    0,
    0,
    0,
    0
  ],
  "Man United": [
    0,
    5,
    28,
    119,
    421,
    1235,
    1943,
    1892,
    1513,
    1130,
    778,
    520,
    267,
    97,
    42,
    10,
    0,
    0,
    0,
    0
  ],
  "Wolves": [
    0,
    0,
    0,
    0,
    1,
    7,
    34,
    71,
    145,
    325,
    530,
    958,
    1313,
    1836,
    2036,
    1845,
    758,
    128,
    13,
    0
  ]
}