{
  "Empoli": [
    0,
    0,
    0,
    0,
    0,
    0,
    0,
    0,
    0,
    0,
    2,
    46,
    678,
    1007,
    1362,
    1552,
    1785,
    1907,
    1614,
    47
  ],
  "Verona": [
    0,
    0,
    0,
    0,
    0,
    0,
    0,
    0,
    0,
    3,
    39,
    196,
    1254,
    1568,
    1675,
    1599,
    1471,
    1259,
    890,
    46
  ],
  "Frosinone": [
    0,
    0,
    0,
    0,
    0,
    0,
    0,
    0,
    0,
    19,
    63,
    309,
    1715,
    2009,
    1744,
    1409,
    1151,
    929,
    627,
    25
  ],
  "Napoli": [
    0,
    0,
    14,
    153,
    535,
    1285,
    2687,
    2813,
    2014,
    420,
    72,
    7,
    0,
    0,
    0,
    0,
    0,
    0,
    0,
    0
  ],
  "Genoa": [
    0,
    0,
    0,
    0,
    0,
    0,
    14,
    64,
    325,
    1737,
    2930,
    4015,
    686,
    171,
    48,
    9,
    1,
    0,
    0,
    0
  ],
  "Fiorentina": [
    0,
    2,
    14,
    149,
    508,
    1311,
    2687,
    2805,
    2050,
    387,
    75,
    12,
    0,
    0,
    0,
    0,
    0,
    0,
    0,
    0
  ],
  "Inter": [
    10000,
    0,
    0,
    0,
    0,
    0,
    0,
    0,
    0,
    0,
    0,
    0,
    0,
    0,
    0,
    0,
    0,
    0,
    0,
    0
  ],
  "Monza": [
    0,
    0,
    0,
    0,
    0,
    1,
    38,
    168,
    677,
    2765,
    3196,
    2728,
    368,
    54,
    5,
    0,
    0,
    0,
    0,
    0
  ],
  "Roma": [
    0,
    81,
    362,
    1675,
    2537,
    2990,
    1454,
    658,
    228,
    14,
    1,
    0,
    0,
    0,
    0,
    0,
    0,
    0,
    0,
    0
  ],
  "Salernitana": [
    0,
    0,
    0,
    0,
    0,
    0,
    0,
    0,
    0,
    0,
    0,
    0,
    0,
    3,
    1,
    12,
    36,
    108,
    475,
    9365
  ],
  "Sassuolo": [
    0,
    0,
    0,
    0,
    0,
    0,
    0,
    0,
    0,
    0,
    3,
    30,
    401,
    683,
    939,
    1269,
    1572,
    1884,
    2920,
    299
  ],
  "Atalanta": [
    0,
    93,
    525,
    2141,
    3214,
    2434,
    1012,
    425,
    150,
    6,
    0,
    0,
    0,
    0,
    0,
    0,
    0,
    0,
    0,
    0
  ],
  "Lecce": [
    0,
    0,
    0,
    0,
    0,
    0,
    0,
    0,
    1,
    22,
    110,
    482,
    2925,
    2063,
    1548,
    1162,
    782,
    547,
    342,
    16
  ],
  "Lazio": [
    0,
    0,
    0,
    23,
    125,
    471,
    1565,
    2719,
    3764,
    1001,
    263,
    69,
    0,
    0,
    0,
    0,
    0,
    0,
    0,
    0
  ],
  "Udinese": [
    0,
    0,
    0,
    0,
    0,
    0,
    0,
    0,
    0,
    3,
    18,
    132,
    1226,
    1504,
    1526,
    1572,
    1485,
    1379,
    1100,
    55
  ],
  "Juventus": [
    0,
    4535,
    4047,
    1029,
    308,
    67,
    12,
    2,
    0,
    0,
    0,
    0,
    0,
    0,
    0,
    0,
    0,
    0,
    0,
    0
  ],
  "Torino": [
    0,
    0,
    0,
    0,
    1,
    7,
    55,
    207,
    769,
    3623,
    3222,
    1907,
    183,
    23,
    2,
    1,
    0,
    0,
    0,
    0
  ],
  "Cagliari": [
    0,
    0,
    0,
    0,
    0,
    0,
    0,
    0,
    0,
    0,
    6,
    67,
    564,
    915,
    1150,
    1415,
    1717,
    1987,
    2032,
    147
  ],
  "Bologna": [
    0,
    266,
    1141,
    4001,
    2563,
    1395,
    473,
    139,
    22,
    0,
    0,
    0,
    0,
    0,
    0,
    0,
    0,
    0,
    0,
    0
  ],
  "Milan": [
    0,
    5023,
    3897,
    829,
    209,
    39,
    3,
    0,
    0,
    0,
    0,
    0,
    0,
    0,
    0,
    0,
    0,
    0,
    0,
    0
  ]
}