{
  "Lyon": [
    0,
    0,
    0,
    5,
    47,
    402,
    1602,
    2571,
    2040,
    1435,
    959,
    566,
    251,
    90,
    23,
    8,
    1,
    0,
    0,
    0
  ],
  "Ajaccio": [
    0,
    0,
    0,
    0,
    0,
    0,
    0,
    0,
    1,
    2,
    6,
    20,
    68,
    226,
    604,
    1274,
    2422,
    3249,
    1694,
    434
  ],
  "Strasbourg": [
    0,
    0,
    0,
    0,
    0,
    0,
    0,
    4,
    13,
    24,
    94,
    253,
    588,
    1183,
    1948,
    2518,
    1832,
    1101,
    374,
    68
  ],
  "Monaco": [
    12,
    254,
    974,
    3319,
    3514,
    1543,
    328,
    46,
    7,
    1,
    2,
    0,
    0,
    0,
    0,
    0,
    0,
    0,
    0,
    0
  ],
  "Clermont": [
    0,
    0,
    0,
    2,
    13,
    166,
    879,
    1771,
    2149,
    1909,
    1457,
    947,
    450,
    172,
    69,
    13,
    3,
    0,
    0,
    0
  ],
  "Paris SG": [
    8681,
    1074,
    229,
    15,
    1,
    0,
    0,
    0,
    0,
    0,
    0,
    0,
    0,
    0,
    0,
    0,
    0,
    0,
    0,
    0
  ],
  "Toulouse": [
    0,
    0,
    0,
    0,
    3,
    20,
    164,
    491,
    835,
    1324,
    1763,
    1940,
    1727,
    997,
    499,
    185,
    46,
    5,
    1,
    0
  ],
  "Nice": [
    0,
    0,
    0,
    0,
    13,
    125,
    771,
    1586,
    2026,
    1971,
    1570,
    1065,
    522,
    262,
    72,
    17,
    0,
    0,
    0,
    0
  ],
  "Angers": [
    0,
    0,
    0,
    0,
    0,
    0,
    0,
    0,
    0,
    0,
    0,
    0,
    0,
    1,
    15,
    53,
    226,
    654,
    2109,
    6942
  ],
  "Nantes": [
    0,
    0,
    0,
    0,
    0,
    2,
    58,
    171,
    454,
    737,
    1306,
    1860,
    2357,
    1615,
    839,
    400,
    162,
    37,
    2,
    0
  ],
  "Lens": [
    716,
    4182,
    3773,
    1002,
    279,
    44,
    4,
    0,
    0,
    0,
    0,
    0,
    0,
    0,
    0,
    0,
    0,
    0,
    0,
    0
  ],
  "Brest": [
    0,
    0,
    0,
    0,
    0,
    0,
    0,
    0,
    0,
    11,
    12,
    48,
    185,
    490,
    1080,
    1898,
    2635,
    2333,
    1099,
    209
  ],
  "Lille": [
    0,
    15,
    123,
    844,
    2054,
    4688,
    1641,
    465,
    102,
    48,
    14,
    5,
    1,
    0,
    0,
    0,
    0,
    0,
    0,
    0
  ],
  "Auxerre": [
    0,
    0,
    0,
    0,
    0,
    0,
    0,
    0,
    0,
    0,
    1,
    1,
    7,
    40,
    113,
    329,
    799,
    1851,
    4527,
    2332
  ],
  "Montpellier": [
    0,
    0,
    0,
    0,
    0,
    0,
    2,
    13,
    33,
    110,
    235,
    545,
    1054,
    1980,
    2348,
    1874,
    1165,
    500,
    131,
    10
  ],
  "Troyes": [
    0,
    0,
    0,
    0,
    0,
    0,
    5,
    23,
    79,
    219,
    432,
    847,
    1525,
    2332,
    2150,
    1360,
    691,
    269,
    63,
    5
  ],
  "Rennes": [
    12,
    307,
    1101,
    3586,
    3406,
    1325,
    222,
    36,
    4,
    1,
    0,
    0,
    0,
    0,
    0,
    0,
    0,
    0,
    0,
    0
  ],
  "Lorient": [
    0,
    2,
    9,
    88,
    378,
    1612,
    4049,
    2035,
    976,
    502,
    236,
    80,
    23,
    9,
    0,
    1,
    0,
    0,
    0,
    0
  ],
  "Marseille": [
    579,
    4166,
    3791,
    1139,
    290,
    34,
    1,
    0,
    0,
    0,
    0,
    0,
    0,
    0,
    0,
    0,
    0,
    0,
    0,
    0
  ],
  "Reims": [
    0,
    0,
    0,
    0,
    2,
    39,
    274,
    788,
    1281,
    1706,
    1913,
    1823,
    1242,
    603,
    240,
    70,
    18,
    1,
    0,
    0
  ]
}