{
  "Burnley": [
    0,
    0,
    0,
    0,
    0,
    0,
    0,
    0,
    0,
    0,
    0,
    0,
    0,
    7,
    25,
    92,
    429,
    1566,
    5061,
    2820
  ],
  "Man City": [
    1974,
    2812,
    3703,
    1400,
    109,
    2,
    0,
    0,
    0,
    0,
    0,
    0,
    0,
    0,
    0,
    0,
    0,
    0,
    0,
    0
  ],
  "Arsenal": [
    3074,
    3350,
    2647,
    862,
    65,
    2,
    0,
    0,
    0,
    0,
    0,
    0,
    0,
    0,
    0,
    0,
    0,
    0,
    0,
    0
  ],
  "Nott'm Forest": [
    0,
    0,
    0,
    0,
    0,
    0,
    0,
    1,
    7,
    29,
    65,
    151,
    341,
    651,
    1122,
    1824,
    2905,
    2140,
    679,
    85
  ],
  "Bournemouth": [
    0,
    0,
    0,
    0,
    0,
    0,
    2,
    23,
    47,
    98,
    239,
    466,
    985,
    1541,
    1876,
    2264,
    1644,
    748,
    64,
    3
  ],
  "West Ham": [
    0,
    0,
    0,
    25,
    430,
    1181,
    2349,
    1977,
    1565,
    1098,
    758,
    404,
    165,
    33,
    13,
    2,
    0,
    0,
    0,
    0
  ],
  "Brighton": [
    0,
    0,
    1,
    0,
    73,
    322,
    866,
    1387,
    1671,
    1760,
    1626,
    1158,
    658,
    302,
    129,
    38,
    8,
    1,
    0,
    0
  ],
  "Luton": [
    0,
    0,
    0,
    0,
    0,
    0,
    0,
    1,
    4,
    3,
    19,
    59,
    165,
    335,
    644,
    1073,
    1977,
    3839,
    1515,
    366
  ],
  "Everton": [
    0,
    0,
    0,
    0,
    0,
    1,
    6,
    15,
    54,
    146,
    304,
    661,
    1332,
    1921,
    2095,
    1824,
    1162,
    433,
    45,
    1
  ],
  "Fulham": [
    0,
    0,
    0,
    0,
    21,
    91,
    408,
    756,
    1163,
    1580,
    1808,
    1769,
    1226,
    695,
    336,
    109,
    35,
    3,
    0,
    0
  ],
  "Sheffield United": [
    0,
    0,
    0,
    0,
    0,
    0,
    0,
    0,
    0,
    0,
    0,
    0,
    0,
    0,
    2,
    24,
    95,
    592,
    2565,
    6722
  ],
  "Crystal Palace": [
    0,
    0,
    0,
    0,
    0,
    0,
    16,
    38,
    90,
    201,
    371,
    718,
    1292,
    1840,
    1959,
    1677,
    1228,
    515,
    53,
    2
  ],
  "Newcastle": [
    0,
    0,
    0,
    12,
    265,
    802,
    1916,
    2029,
    1815,
    1324,
    877,
    570,
    248,
    111,
    19,
    11,
    1,
    0,
    0,
    0
  ],
  "Aston Villa": [
    247,
    734,
    1751,
    5833,
    1199,
    205,
    29,
    2,
    0,
    0,
    0,
    0,
    0,
    0,
    0,
    0,
    0,
    0,
    0,
    0
  ],
  "Brentford": [
    0,
    0,
    0,
    0,
    0,
    1,
    39,
    116,
    268,
    545,
    910,
    1429,
    2027,
    1706,
    1398,
    913,
    469,
    160,
    18,
    1
  ],
  "Tottenham": [
    7,
    29,
    144,
    1112,
    5113,
    2385,
    774,
    309,
    97,
    28,
    1,
    1,
    0,
    0,
    0,
    0,
    0,
    0,
    0,
    0
  ],
  "Chelsea": [
    0,
    0,
    0,
    2,
    46,
    230,
    644,
    923,
    1177,
    1440,
    1722,
    1658,
    1056,
    630,
    311,
    119,
    40,
    2,
    0,
    0
  ],
  "Liverpool": [
    4698,
    3074,
    1739,
    475,
    14,
    0,
    0,
    0,
    0,
    0,
    0,
    0,
    0,
    0,
    0,
    0,
    0,
    0,
    0,
    0
  ],
  "Man United": [
    0,
    1,
    15,
    275,
    2546,
    4302,
    1692,
    740,
    285,
    99,
    36,
    8,
    1,
    0,
    0,
    0,
    0,
    0,
    0,
    0
  ],
  "Wolves": [
    0,
    0,
    0,
    4,
    119,
    476,
    1259,
    1683,
    1757,
    1649,
    1264,
    948,
    504,
    228,
    71,
    30,
    7,
    1,
    0,
    0
  ]
}