{
  "Ein Frankfurt": [
    250,
    1328,
    2318,
    2235,
    1698,
    1089,
    596,
    311,
    99,
    54,
    19,
    2,
    1,
    0,
    0,
    0,
    0,
    0
  ],
  "Bayern Munich": [
    2024,
    4186,
    2090,
    984,
    468,
    189,
    54,
    5,
    0,
    0,
    0,
    0,
    0,
    0,
    0,
    0,
    0,
    0
  ],
  "Augsburg": [
    0,
    0,
    0,
    0,
    2,
    1,
    3,
    22,
    47,
    165,
    321,
    674,
    1325,
    1869,
    2134,
    1826,
    1200,
    411
  ],
  "Freiburg": [
    11,
    141,
    422,
    819,
    1370,
    1922,
    2246,
    1514,
    967,
    388,
    156,
    36,
    6,
    2,
    0,
    0,
    0,
    0
  ],
  "Bochum": [
    0,
    0,
    0,
    0,
    0,
    0,
    0,
    3,
    10,
    27,
    69,
    200,
    447,
    829,
    1369,
    1906,
    2630,
    2510
  ],
  "Mainz": [
    1,
    10,
    65,
    146,
    316,
    678,
    1071,
    1667,
    2040,
    1675,
    1217,
    693,
    294,
    97,
    24,
    6,
    0,
    0
  ],
  "M'gladbach": [
    0,
    1,
    7,
    15,
    55,
    157,
    399,
    781,
    1128,
    1784,
    1991,
    1753,
    991,
    548,
    265,
    88,
    31,
    6
  ],
  "Hoffenheim": [
    0,
    0,
    0,
    0,
    0,
    0,
    2,
    5,
    15,
    69,
    172,
    450,
    842,
    1342,
    1698,
    2032,
    1939,
    1434
  ],
  "Union Berlin": [
    357,
    1412,
    2418,
    2243,
    1714,
    1028,
    520,
    221,
    55,
    28,
    4,
    0,
    0,
    0,
    0,
    0,
    0,
    0
  ],
  "Hertha": [
    0,
    0,
    0,
    0,
    0,
    2,
    6,
    19,
    66,
    172,
    375,
    778,
    1314,
    1656,
    1764,
    1668,
    1344,
    836
  ],
  "Wolfsburg": [
    13,
    179,
    579,
    1095,
    1585,
    2120,
    1821,
    1208,
    737,
    404,
    161,
    74,
    19,
    5,
    0,
    0,
    0,
    0
  ],
  "Werder Bremen": [
    1,
    3,
    4,
    23,
    74,
    184,
    400,
    796,
    1222,
    1533,
    1934,
    1708,
    1114,
    584,
    278,
    106,
    34,
    2
  ],
  "Dortmund": [
    7220,
    1969,
    583,
    164,
    56,
    8,
    0,
    0,
    0,
    0,
    0,
    0,
    0,
    0,
    0,
    0,
    0,
    0
  ],
  "Leverkusen": [
    0,
    13,
    84,
    229,
    414,
    811,
    1392,
    1933,
    1772,
    1442,
    974,
    550,
    244,
    107,
    28,
    7,
    0,
    0
  ],
  "Stuttgart": [
    0,
    0,
    0,
    0,
    0,
    0,
    0,
    0,
    2,
    10,
    23,
    49,
    207,
    458,
    777,
    1440,
    2354,
    4680
  ],
  "RB Leipzig": [
    123,
    758,
    1428,
    2031,
    2186,
    1617,
    989,
    524,
    231,
    85,
    23,
    5,
    0,
    0,
    0,
    0,
    0,
    0
  ],
  "FC Koln": [
    0,
    0,
    2,
    16,
    62,
    194,
    493,
    963,
    1477,
    1837,
    1850,
    1486,
    829,
    459,
    213,
    80,
    34,
    5
  ],
  "Schalke 04": [
    0,
    0,
    0,
    0,
    0,
    0,
    8,
    28,
    132,
    327,
    711,
    1542,
    2367,
    2044,
    1450,
    841,
    434,
    116
  ]
}