{
  "Heerenveen": [
    0,
    0,
    0,
    1,
    13,
    155,
    603,
    1379,
    2566,
    2261,
    1814,
    993,
    184,
    28,
    3,
    0,
    0,
    0
  ],
  "Willem II": [
    0,
    0,
    0,
    0,
    0,
    0,
    0,
    0,
    0,
    0,
    0,
    3,
    33,
    220,
    1142,
    5112,
    3108,
    382
  ],
  "Zwolle": [
    0,
    0,
    0,
    0,
    0,
    0,
    0,
    3,
    29,
    77,
    278,
    1077,
    3585,
    3289,
    1512,
    140,
    10,
    0
  ],
  "Feyenoord": [
    1,
    1906,
    3532,
    2465,
    1427,
    535,
    120,
    12,
    2,
    0,
    0,
    0,
    0,
    0,
    0,
    0,
    0,
    0
  ],
  "Twente": [
    0,
    1,
    38,
    140,
    481,
    1698,
    3197,
    2546,
    1098,
    510,
    233,
    52,
    6,
    0,
    0,
    0,
    0,
    0
  ],
  "For Sittard": [
    0,
    0,
    2,
    0,
    7,
    88,
    355,
    889,
    1996,
    2571,
    2427,
    1389,
    228,
    44,
    4,
    0,
    0,
    0
  ],
  "FC Emmen": [
    0,
    0,
    0,
    0,
    0,
    0,
    0,
    0,
    0,
    0,
    0,
    0,
    0,
    2,
    10,
    181,
    1215,
    8592
  ],
  "VVV Venlo": [
    0,
    0,
    0,
    0,
    0,
    0,
    1,
    0,
    26,
    81,
    296,
    987,
    2987,
    3445,
    1935,
    231,
    10,
    1
  ],
  "Heracles": [
    0,
    0,
    0,
    0,
    5,
    44,
    235,
    719,
    1800,
    2322,
    2497,
    1808,
    458,
    94,
    18,
    0,
    0,
    0
  ],
  "Den Haag": [
    0,
    0,
    0,
    0,
    0,
    0,
    0,
    0,
    0,
    0,
    0,
    1,
    10,
    77,
    476,
    2971,
    5447,
    1018
  ],
  "Sparta Rotterdam": [
    0,
    0,
    0,
    0,
    1,
    13,
    68,
    254,
    760,
    1399,
    2075,
    3391,
    1394,
    516,
    125,
    4,
    0,
    0
  ],
  "Ajax": [
    9980,
    19,
    1,
    0,
    0,
    0,
    0,
    0,
    0,
    0,
    0,
    0,
    0,
    0,
    0,
    0,
    0,
    0
  ],
  "Groningen": [
    0,
    54,
    313,
    792,
    1691,
    3889,
    2073,
    859,
    230,
    76,
    21,
    1,
    1,
    0,
    0,
    0,
    0,
    0
  ],
  "PSV Eindhoven": [
    18,
    6554,
    2129,
    878,
    335,
    81,
    4,
    1,
    0,
    0,
    0,
    0,
    0,
    0,
    0,
    0,
    0,
    0
  ],
  "Waalwijk": [
    0,
    0,
    0,
    0,
    0,
    0,
    0,
    2,
    2,
    5,
    42,
    204,
    1108,
    2284,
    4775,
    1361,
    210,
    7
  ],
  "Vitesse": [
    0,
    540,
    1577,
    2528,
    3316,
    1470,
    443,
    112,
    14,
    0,
    0,
    0,
    0,
    0,
    0,
    0,
    0,
    0
  ],
  "Utrecht": [
    0,
    2,
    14,
    54,
    329,
    1143,
    2678,
    3195,
    1471,
    696,
    317,
    94,
    6,
    1,
    0,
    0,
    0,
    0
  ],
  "AZ Alkmaar": [
    1,
    924,
    2394,
    3142,
    2395,
    884,
    223,
    29,
    6,
    2,
    0,
    0,
    0,
    0,
    0,
    0,
    0,
    0
  ]
}